<?xml version="1.0" encoding="utf-8"?>
<!-- Translation by Toys®Us -->
<GameData>
	<Language_fr_FR>
		<Update>
			<Where Tag="TXT_KEY_WONDER_HIMEJI_CASTLE_HELP" />
			<Set Text="+25% [ICON_STRENGTH] de puissance de combat en territoire allié" />
		</Update>
		<Update>
			<Where Tag="TXT_KEY_PROMOTION_GREAT_LIGHTHOUSE_HELP" />
			<Set Text="+1 [ICON_MOVES] en mouvement et +1 en champ de vision" />
		</Update>
		<Update>
			<Where Tag="TXT_KEY_PROMOTION_MORALE_HELP" />
			<Set Text="+15% [ICON_STRENGTH] de puissance de combat" />
		</Update>
	</Language_fr_FR>
</GameData>